torchxrayvision/__init__.py
torchxrayvision/_version.py
torchxrayvision/autoencoders.py
torchxrayvision/datasets.py
torchxrayvision/models.py
torchxrayvision/utils.py
torchxrayvision/baseline_models/__init__.py
torchxrayvision/baseline_models/chestx_det/__init__.py
torchxrayvision/baseline_models/chestx_det/ptsemseg/__init__.py
torchxrayvision/baseline_models/chestx_det/ptsemseg/pspnet.py
torchxrayvision/baseline_models/chestx_det/ptsemseg/utils.py
torchxrayvision/baseline_models/chexpert/__init__.py
torchxrayvision/baseline_models/chexpert/model.py
torchxrayvision/baseline_models/chexpert/predict_configs.json
torchxrayvision/baseline_models/emory_hiti/__init__.py
torchxrayvision/baseline_models/jfhealthcare/__init__.py
torchxrayvision/baseline_models/jfhealthcare/config/__init__.py
torchxrayvision/baseline_models/jfhealthcare/config/example.json
torchxrayvision/baseline_models/jfhealthcare/model/__init__.py
torchxrayvision/baseline_models/jfhealthcare/model/attention_map.py
torchxrayvision/baseline_models/jfhealthcare/model/classifier.py
torchxrayvision/baseline_models/jfhealthcare/model/global_pool.py
torchxrayvision/baseline_models/jfhealthcare/model/utils.py
torchxrayvision/baseline_models/jfhealthcare/model/backbone/__init__.py
torchxrayvision/baseline_models/jfhealthcare/model/backbone/densenet.py
torchxrayvision/baseline_models/jfhealthcare/model/backbone/inception.py
torchxrayvision/baseline_models/jfhealthcare/model/backbone/vgg.py
torchxrayvision/baseline_models/mira/__init__.py
torchxrayvision/baseline_models/riken/__init__.py
torchxrayvision/baseline_models/xinario/__init__.py
torchxrayvision/data/BBox_List_2017.csv.gz
torchxrayvision/data/Data_Entry_2017_v2020.csv.gz
torchxrayvision/data/NLMCXR_reports.tgz
torchxrayvision/data/PADCHEST_chest_x_ray_images_labels_160K_01.02.19.csv.gz
torchxrayvision/data/chexpert_train.csv.gz
torchxrayvision/data/google2019_nih-chest-xray-labels.csv.gz
torchxrayvision/data/kaggle_stage_2_train_images_dicom_headers.csv.gz
torchxrayvision-1.4.0.dist-info/LICENSE
torchxrayvision-1.4.0.dist-info/METADATA
torchxrayvision-1.4.0.dist-info/WHEEL
torchxrayvision-1.4.0.dist-info/top_level.txt
torchxrayvision-1.4.0.dist-info/RECORD
