Metadata-Version: 2.1
Name: torchxrayvision
Version: 1.4.0
Summary: TorchXRayVision: A library of chest X-ray datasets and models
Home-page: https://github.com/mlmed/torchxrayvision
Author: Joseph Paul Cohen
Author-email: joseph@josephpcohen.com
Classifier: Programming Language :: Python :: 3
Classifier: License :: OSI Approved :: Apache Software License
Classifier: Operating System :: OS Independent
Classifier: Topic :: Scientific/Engineering :: Medical Science Apps.
Requires-Python: >=3.6
License-File: LICENSE
Requires-Dist: torch >=1
Requires-Dist: torchvision >=0.5
Requires-Dist: scikit-image >=0.16
Requires-Dist: tqdm >=4
Requires-Dist: numpy >=1
Requires-Dist: pandas >=1
Requires-Dist: requests >=1
Requires-Dist: pillow >=5.3.0
Requires-Dist: imageio
